django_file_upload/__init__.py
django_file_upload/admin.py
django_file_upload/models.py
django_file_upload/tests.py
django_file_upload/urls.py
django_file_upload/views.py
django_file_upload-1.1.6.dist-info/METADATA
django_file_upload-1.1.6.dist-info/WHEEL
django_file_upload-1.1.6.dist-info/top_level.txt
django_file_upload-1.1.6.dist-info/RECORD
