Metadata-Version: 2.1
Name: django-file-upload
Version: 1.1.6
Summary: Django File Upload
Home-page: https://github.com/django-xxx/django-file-upload
Author: Hackathon
Author-email: kimi.huang@brightcells.com
Keywords: Django File Upload
Classifier: Development Status :: 5 - Production/Stable
Classifier: Environment :: Web Environment
Classifier: Framework :: Django
Classifier: Intended Audience :: Developers
Classifier: Programming Language :: Python
Classifier: Topic :: Software Development :: Libraries :: Python Modules
Classifier: Topic :: Office/Business :: Financial :: Spreadsheet
Requires-Dist: TimeConvert
Requires-Dist: django-file-md5 (>=1.0.2)
Requires-Dist: django-logit (>=1.1.2)
Requires-Dist: django-query
Requires-Dist: django-response
Requires-Dist: django-six
